ShumeiPaiJisuanjiShijueBianchengChuyiFix1/README.md
ShumeiPaiJisuanjiShijueBianchengChuyiFix1/__init__.py
ShumeiPaiJisuanjiShijueBianchengChuyiFix1/__main__.py
ShumeiPaiJisuanjiShijueBianchengChuyiFix1/file.epub
ShumeiPaiJisuanjiShijueBianchengChuyiFix1/index.html
ShumeiPaiJisuanjiShijueBianchengChuyiFix1/css/__init__.py
ShumeiPaiJisuanjiShijueBianchengChuyiFix1/css/annotations.css
ShumeiPaiJisuanjiShijueBianchengChuyiFix1/css/main.css
ShumeiPaiJisuanjiShijueBianchengChuyiFix1/css/normalize.css
ShumeiPaiJisuanjiShijueBianchengChuyiFix1/css/popup.css
ShumeiPaiJisuanjiShijueBianchengChuyiFix1/font/__init__.py
ShumeiPaiJisuanjiShijueBianchengChuyiFix1/font/fontello.eot
ShumeiPaiJisuanjiShijueBianchengChuyiFix1/font/fontello.svg
ShumeiPaiJisuanjiShijueBianchengChuyiFix1/font/fontello.ttf
ShumeiPaiJisuanjiShijueBianchengChuyiFix1/font/fontello.woff
ShumeiPaiJisuanjiShijueBianchengChuyiFix1/img/__init__.py
ShumeiPaiJisuanjiShijueBianchengChuyiFix1/img/annotator-glyph-sprite.png
ShumeiPaiJisuanjiShijueBianchengChuyiFix1/img/annotator-icon-sprite.png
ShumeiPaiJisuanjiShijueBianchengChuyiFix1/img/apple-touch-icon.png
ShumeiPaiJisuanjiShijueBianchengChuyiFix1/img/cancelfullscreen.png
ShumeiPaiJisuanjiShijueBianchengChuyiFix1/img/close.png
ShumeiPaiJisuanjiShijueBianchengChuyiFix1/img/fullscreen.png
ShumeiPaiJisuanjiShijueBianchengChuyiFix1/img/loader.gif
ShumeiPaiJisuanjiShijueBianchengChuyiFix1/img/menu-icon.png
ShumeiPaiJisuanjiShijueBianchengChuyiFix1/img/save.png
ShumeiPaiJisuanjiShijueBianchengChuyiFix1/img/saved.png
ShumeiPaiJisuanjiShijueBianchengChuyiFix1/img/settings-s.png
ShumeiPaiJisuanjiShijueBianchengChuyiFix1/img/settings.png
ShumeiPaiJisuanjiShijueBianchengChuyiFix1/img/star.png
ShumeiPaiJisuanjiShijueBianchengChuyiFix1/js/__init__.py
ShumeiPaiJisuanjiShijueBianchengChuyiFix1/js/epub.js
ShumeiPaiJisuanjiShijueBianchengChuyiFix1/js/epub.min.js
ShumeiPaiJisuanjiShijueBianchengChuyiFix1/js/epub.min.map
ShumeiPaiJisuanjiShijueBianchengChuyiFix1/js/hooks.min.js
shumei_pai_jisuanji_shijue_biancheng_chuyi_fix1-2025.3.25.1.dist-info/METADATA
shumei_pai_jisuanji_shijue_biancheng_chuyi_fix1-2025.3.25.1.dist-info/WHEEL
shumei_pai_jisuanji_shijue_biancheng_chuyi_fix1-2025.3.25.1.dist-info/entry_points.txt
shumei_pai_jisuanji_shijue_biancheng_chuyi_fix1-2025.3.25.1.dist-info/top_level.txt
shumei_pai_jisuanji_shijue_biancheng_chuyi_fix1-2025.3.25.1.dist-info/RECORD
